Workbook

Sheet Simulador
A1: Simulador de Investimentos em Fundos Imobiliários (FIIs)
A2: Modelo educacional para simular aportes, patrimônio e dividendos ao longo do tempo.
A4: PARÂMETROS DA SIMULAÇÃO
A5: Investimento inicial | B5: 5000
A6: Aporte mensal | B6: 1000
A7: Dividend yield mensal | B7: 0.008
A8: Valorização anual estimada | B8: 0.05
A9: Prazo (anos) | B9: 10
A11: Indicadores principais
A12: Total investido | B12: =B5+B6*B9*12
A13: Patrimônio final estimado | B13: =INDEX($F$16:$F$135,$B$9*12)
A14: Dividendos mensais no final | B14: =INDEX($G$16:$G$135,$B$9*12)
A16: Observação | B16: Os resultados são projeções e não representam garantia de rentabilidade. Dividendos e preços de FIIs variam ao longo do tempo.
A19: Mês | B19: Ano | C19: Aporte | D19: Total investido | E19: Patrimônio inicial | F19: Patrimônio final | G19: Dividendos mensais | H19: Dividendos acumulados
A20: 1 | B20: =ROUND(A20/12,0) | C20: =IF(A20<=$B$9*12,$B$6,0) | D20: =IF(A20=1,$B$5+C20,D19+C20) | E20: =IF(A20=1,$B$5,F19) | F20: =IF(A20<=$B$9*12,E20*(1+$B$8)^(1/12)+C20,0) | G20: =IF(A20<=$B$9*12,F20*$B$7,0) | H20: =IF(A20=1,G20,H19+G20)
A21: 2 | B21: =ROUND(A21/12,0) | C21: =IF(A21<=$B$9*12,$B$6,0) | D21: =IF(A21=1,$B$5+C21,D20+C21) | E21: =IF(A21=1,$B$5,F20) | F21: =IF(A21<=$B$9*12,E21*(1+$B$8)^(1/12)+C21,0) | G21: =IF(A21<=$B$9*12,F21*$B$7,0) | H21: =IF(A21=1,G21,H20+G21)
A22: 3 | B22: =ROUND(A22/12,0) | C22: =IF(A22<=$B$9*12,$B$6,0) | D22: =IF(A22=1,$B$5+C22,D21+C22) | E22: =IF(A22=1,$B$5,F21) | F22: =IF(A22<=$B$9*12,E22*(1+$B$8)^(1/12)+C22,0) | G22: =IF(A22<=$B$9*12,F22*$B$7,0) | H22: =IF(A22=1,G22,H21+G22)
A23: 4 | B23: =ROUND(A23/12,0) | C23: =IF(A23<=$B$9*12,$B$6,0) | D23: =IF(A23=1,$B$5+C23,D22+C23) | E23: =IF(A23=1,$B$5,F22) | F23: =IF(A23<=$B$9*12,E23*(1+$B$8)^(1/12)+C23,0) | G23: =IF(A23<=$B$9*12,F23*$B$7,0) | H23: =IF(A23=1,G23,H22+G23)
A24: 5 | B24: =ROUND(A24/12,0) | C24: =IF(A24<=$B$9*12,$B$6,0) | D24: =IF(A24=1,$B$5+C24,D23+C24) | E24: =IF(A24=1,$B$5,F23) | F24: =IF(A24<=$B$9*12,E24*(1+$B$8)^(1/12)+C24,0) | G24: =IF(A24<=$B$9*12,F24*$B$7,0) | H24: =IF(A24=1,G24,H23+G24)
A25: 6 | B25: =ROUND(A25/12,0) | C25: =IF(A25<=$B$9*12,$B$6,0) | D25: =IF(A25=1,$B$5+C25,D24+C25) | E25: =IF(A25=1,$B$5,F24) | F25: =IF(A25<=$B$9*12,E25*(1+$B$8)^(1/12)+C25,0) | G25: =IF(A25<=$B$9*12,F25*$B$7,0) | H25: =IF(A25=1,G25,H24+G25)
A26: 7 | B26: =ROUND(A26/12,0) | C26: =IF(A26<=$B$9*12,$B$6,0) | D26: =IF(A26=1,$B$5+C26,D25+C26) | E26: =IF(A26=1,$B$5,F25) | F26: =IF(A26<=$B$9*12,E26*(1+$B$8)^(1/12)+C26,0) | G26: =IF(A26<=$B$9*12,F26*$B$7,0) | H26: =IF(A26=1,G26,H25+G26)
A27: 8 | B27: =ROUND(A27/12,0) | C27: =IF(A27<=$B$9*12,$B$6,0) | D27: =IF(A27=1,$B$5+C27,D26+C27) | E27: =IF(A27=1,$B$5,F26) | F27: =IF(A27<=$B$9*12,E27*(1+$B$8)^(1/12)+C27,0) | G27: =IF(A27<=$B$9*12,F27*$B$7,0) | H27: =IF(A27=1,G27,H26+G27)
A28: 9 | B28: =ROUND(A28/12,0) | C28: =IF(A28<=$B$9*12,$B$6,0) | D28: =IF(A28=1,$B$5+C28,D27+C28) | E28: =IF(A28=1,$B$5,F27) | F28: =IF(A28<=$B$9*12,E28*(1+$B$8)^(1/12)+C28,0) | G28: =IF(A28<=$B$9*12,F28*$B$7,0) | H28: =IF(A28=1,G28,H27+G28)
A29: 10 | B29: =ROUND(A29/12,0) | C29: =IF(A29<=$B$9*12,$B$6,0) | D29: =IF(A29=1,$B$5+C29,D28+C29) | E29: =IF(A29=1,$B$5,F28) | F29: =IF(A29<=$B$9*12,E29*(1+$B$8)^(1/12)+C29,0) | G29: =IF(A29<=$B$9*12,F29*$B$7,0) | H29: =IF(A29=1,G29,H28+G29)
A30: 11 | B30: =ROUND(A30/12,0) | C30: =IF(A30<=$B$9*12,$B$6,0) | D30: =IF(A30=1,$B$5+C30,D29+C30) | E30: =IF(A30=1,$B$5,F29) | F30: =IF(A30<=$B$9*12,E30*(1+$B$8)^(1/12)+C30,0) | G30: =IF(A30<=$B$9*12,F30*$B$7,0) | H30: =IF(A30=1,G30,H29+G30)
A31: 12 | B31: =ROUND(A31/12,0) | C31: =IF(A31<=$B$9*12,$B$6,0) | D31: =IF(A31=1,$B$5+C31,D30+C31) | E31: =IF(A31=1,$B$5,F30) | F31: =IF(A31<=$B$9*12,E31*(1+$B$8)^(1/12)+C31,0) | G31: =IF(A31<=$B$9*12,F31*$B$7,0) | H31: =IF(A31=1,G31,H30+G31)
... A139: 120 | B139: =ROUND(A139/12,0) | C139: =IF(A139<=$B$9*12,$B$6,0) | D139: =IF(A139=1,$B$5+C139,D138+C139) | E139: =IF(A139=1,$B$5,F138) | F139: =IF(A139<=$B$9*12,E139*(1+$B$8)^(1/12)+C139,0) | G139: =IF(A139<=$B$9*12,F139*$B$7,0) | H139: =IF(A139=1,G139,H138+G139)

Sheet Resumo
A1: Resumo da Simulação
A3: Ano | B3: Total investido | C3: Patrimônio | D3: Dividendos/mês | E3: Dividendos no ano | F3: Ganho patrimonial
A4: 1 | B4: =Simulador!D31 | C4: =Simulador!F31 | D4: =Simulador!G31 | E4: =Simulador!H31-IF(1=1,0,Simulador!H19) | F4: =C4-B4
A5: 2 | B5: =Simulador!D43 | C5: =Simulador!F43 | D5: =Simulador!G43 | E5: =Simulador!H43-IF(2=1,0,Simulador!H31) | F5: =C5-B5
A6: 3 | B6: =Simulador!D55 | C6: =Simulador!F55 | D6: =Simulador!G55 | E6: =Simulador!H55-IF(3=1,0,Simulador!H43) | F6: =C6-B6
A7: 4 | B7: =Simulador!D67 | C7: =Simulador!F67 | D7: =Simulador!G67 | E7: =Simulador!H67-IF(4=1,0,Simulador!H55) | F7: =C7-B7
A8: 5 | B8: =Simulador!D79 | C8: =Simulador!F79 | D8: =Simulador!G79 | E8: =Simulador!H79-IF(5=1,0,Simulador!H67) | F8: =C8-B8
A9: 6 | B9: =Simulador!D91 | C9: =Simulador!F91 | D9: =Simulador!G91 | E9: =Simulador!H91-IF(6=1,0,Simulador!H79) | F9: =C9-B9
A10: 7 | B10: =Simulador!D103 | C10: =Simulador!F103 | D10: =Simulador!G103 | E10: =Simulador!H103-IF(7=1,0,Simulador!H91) | F10: =C10-B10
A11: 8 | B11: =Simulador!D115 | C11: =Simulador!F115 | D11: =Simulador!G115 | E11: =Simulador!H115-IF(8=1,0,Simulador!H103) | F11: =C11-B11
A12: 9 | B12: =Simulador!D127 | C12: =Simulador!F127 | D12: =Simulador!G127 | E12: =Simulador!H127-IF(9=1,0,Simulador!H115) | F12: =C12-B12
A13: 10 | B13: =Simulador!D139 | C13: =Simulador!F139 | D13: =Simulador!G139 | E13: =Simulador!H139-IF(10=1,0,Simulador!H127) | F13: =C13-B13
